{
  "generated": "2026-03-07T02:33:44.542353-05:00",
  "run_time": "02:33 ET",
  "run_type": "PRE",
  "version": "1.1",
  "overall": {
    "intraday": {
      "score": -3,
      "signal": "BEARISH",
      "confidence": 7,
      "reason": "Broad equity sell-off, rising VIX, and flight to safety in gold/silver."
    },
    "swing": {
      "score": -2,
      "signal": "BEARISH",
      "confidence": 6,
      "reason": "Elevated VIX, falling equities, but strong crude oil and natural gas."
    }
  },
  "asset_classes": {
    "EQUITY_INDEX": {
      "intraday": {
        "score": -4,
        "signal": "STRONG_BEARISH",
        "confidence": 8,
        "reason": "All major indices falling sharply, led by SOX semiconductors. VIX surging."
      },
      "swing": {
        "score": -3,
        "signal": "BEARISH",
        "confidence": 7,
        "reason": "Significant daily declines across the board, VIX backwardation suggests continued stress."
      },
      "symbols": [
        "ES",
        "NQ",
        "YM",
        "RTY",
        "MES",
        "MNQ"
      ]
    },
    "FIXED_INCOME": {
      "intraday": {
        "score": -1,
        "signal": "SLIGHT_BEARISH",
        "confidence": 6,
        "reason": "10Y yield rising slightly, but flight to safety could cap further increases."
      },
      "swing": {
        "score": -1,
        "signal": "SLIGHT_BEARISH",
        "confidence": 5,
        "reason": "10Y yield rising slightly, but overall market uncertainty could lead to demand."
      },
      "symbols": [
        "ZB",
        "ZN",
        "ZT",
        "ZF",
        "GE",
        "SR3"
      ]
    },
    "ENERGY": {
      "intraday": {
        "score": 4,
        "signal": "STRONG_BULLISH",
        "confidence": 8,
        "reason": "Crude oil and natural gas surging, strong bullish signal from EIA draw."
      },
      "swing": {
        "score": 4,
        "signal": "STRONG_BULLISH",
        "confidence": 7,
        "reason": "Significant daily gains in crude and natural gas, EIA draw indicates tightening supply."
      },
      "symbols": [
        "CL",
        "NG",
        "RB",
        "HO",
        "MCL"
      ]
    },
    "METALS": {
      "intraday": {
        "score": 3,
        "signal": "BULLISH",
        "confidence": 7,
        "reason": "Gold and silver rising strongly, indicating flight to safety amidst market turmoil."
      },
      "swing": {
        "score": 2,
        "signal": "BULLISH",
        "confidence": 6,
        "reason": "Strong daily gains in precious metals suggest continued safe-haven demand."
      },
      "symbols": [
        "GC",
        "SI",
        "HG",
        "MGC"
      ]
    },
    "AGRICULTURE": {
      "intraday": {
        "score": 0,
        "signal": "NEUTRAL",
        "confidence": 4,
        "reason": "No direct data points for agriculture, assuming neutral based on lack of drivers."
      },
      "swing": {
        "score": 0,
        "signal": "NEUTRAL",
        "confidence": 4,
        "reason": "No direct data points for agriculture, assuming neutral based on lack of drivers."
      },
      "symbols": [
        "ZC",
        "ZS",
        "ZW",
        "KC",
        "SB",
        "CC",
        "LE",
        "HE"
      ]
    },
    "FX": {
      "intraday": {
        "score": -2,
        "signal": "BEARISH",
        "confidence": 6,
        "reason": "DXY rising, most major pairs falling against USD, indicating USD strength."
      },
      "swing": {
        "score": -1,
        "signal": "SLIGHT_BEARISH",
        "confidence": 5,
        "reason": "USD generally strengthening, but some pairs showing resilience."
      },
      "symbols": [
        "6E",
        "6A",
        "6J",
        "6B",
        "M6E"
      ]
    },
    "CRYPTO": {
      "intraday": {
        "score": -3,
        "signal": "BEARISH",
        "confidence": 6,
        "reason": "Extreme Fear in sentiment, BTC showing slight decline despite overall market stress."
      },
      "swing": {
        "score": -3,
        "signal": "BEARISH",
        "confidence": 5,
        "reason": "Extreme Fear index and negative sentiment suggest continued weakness."
      },
      "symbols": [
        "BTC",
        "ETH",
        "MBT"
      ]
    },
    "VOLATILITY": {
      "intraday": {
        "score": -4,
        "signal": "STRONG_BEARISH",
        "confidence": 8,
        "reason": "VIX surging over 24%, term structure in backwardation, indicating high stress."
      },
      "swing": {
        "score": -3,
        "signal": "BEARISH",
        "confidence": 7,
        "reason": "Elevated VIX and backwardation suggest continued high volatility in the near term."
      },
      "symbols": [
        "VX",
        "VXM"
      ]
    }
  },
  "market_data": {
    "vix": {
      "value": 29.49,
      "trend": "rising",
      "change_1d_pct": 24.17
    },
    "dxy": {
      "value": 98.99,
      "trend": "rising",
      "change_5d": 1.11
    },
    "us10y": {
      "value": 4.133,
      "trend": "rising"
    },
    "real_yield_10y": {
      "value": 1.82,
      "trend": "stable"
    },
    "hy_spread": {
      "value": 3.0,
      "trend": "stable"
    },
    "fed_funds_current": 3.64,
    "breakeven_inflation_10y": 2.35,
    "yield_curve_2s10s": 0.59,
    "vix_term_structure": "backwardation",
    "vix_contango_pct": -7.28,
    "gdpnow_estimate_pct": 4.2,
    "eia_crude_change_mb": null,
    "eia_signal": "draw",
    "crypto_fear_greed": 12,
    "crypto_fear_greed_label": "Extreme Fear",
    "btc_etf_flow_usd_m": null,
    "gold": 5146.1001,
    "crude_oil": 90.9,
    "btc": 67728.5469,
    "sp500": 6740.02,
    "nasdaq": 24643.0195
  },
  "calendar": {
    "high_impact_today": false,
    "high_impact_events": [],
    "fomc_days_away": 11,
    "nfp_days_away": 27,
    "in_blackout": false
  },
  "key_drivers": [
    "Broad equity market sell-off",
    "Surging VIX and backwardation",
    "Strong rally in crude oil and natural gas"
  ],
  "data_quality": {
    "stale_sources": [],
    "fallbacks_used": [],
    "validation_corrections": [],
    "notes": "Generated by Matrix Nano Bias Script v1.2 | Run: PRE"
  }
}