{
  "generated": "2026-03-27T02:34:37.630401-04:00",
  "run_time": "02:34 ET",
  "run_type": "PRE",
  "version": "1.1",
  "overall": {
    "intraday": {
      "score": -3,
      "signal": "BEARISH",
      "confidence": 7,
      "reason": "Broad equity weakness, rising VIX, and falling crypto indicate risk-off sentiment."
    },
    "swing": {
      "score": -3,
      "signal": "BEARISH",
      "confidence": 7,
      "reason": "Rising VIX, higher 10Y yield, and equity weakness suggest continued risk aversion."
    }
  },
  "asset_classes": {
    "EQUITY_INDEX": {
      "intraday": {
        "score": -4,
        "signal": "STRONG_BEARISH",
        "confidence": 8,
        "reason": "All major indices falling significantly, led by tech and semiconductors."
      },
      "swing": {
        "score": -4,
        "signal": "STRONG_BEARISH",
        "confidence": 8,
        "reason": "Broad market sell-off, rising VIX, and higher yields point to sustained pressure."
      },
      "symbols": [
        "ES",
        "NQ",
        "YM",
        "RTY",
        "MES",
        "MNQ"
      ]
    },
    "FIXED_INCOME": {
      "intraday": {
        "score": -2,
        "signal": "BEARISH",
        "confidence": 7,
        "reason": "10Y Treasury yield rising, indicating bond prices falling."
      },
      "swing": {
        "score": -2,
        "signal": "BEARISH",
        "confidence": 7,
        "reason": "Rising 10Y yield and real yield suggest continued pressure on bond prices."
      },
      "symbols": [
        "ZB",
        "ZN",
        "ZT",
        "ZF",
        "GE",
        "SR3"
      ]
    },
    "ENERGY": {
      "intraday": {
        "score": -1,
        "signal": "SLIGHT_BEARISH",
        "confidence": 6,
        "reason": "Crude oil falling, potential for further downside."
      },
      "swing": {
        "score": -1,
        "signal": "SLIGHT_BEARISH",
        "confidence": 6,
        "reason": "Crude oil falling, no strong bullish catalysts."
      },
      "symbols": [
        "CL",
        "NG",
        "RB",
        "HO",
        "MCL"
      ]
    },
    "METALS": {
      "intraday": {
        "score": 2,
        "signal": "BULLISH",
        "confidence": 7,
        "reason": "Gold and silver rising significantly, acting as safe havens amidst risk-off."
      },
      "swing": {
        "score": 3,
        "signal": "BULLISH",
        "confidence": 7,
        "reason": "Safe-haven demand for gold/silver likely to persist with market uncertainty."
      },
      "symbols": [
        "GC",
        "SI",
        "HG",
        "MGC"
      ]
    },
    "AGRICULTURE": {
      "intraday": {
        "score": 0,
        "signal": "NEUTRAL",
        "confidence": 5,
        "reason": "No direct data for agriculture, assuming neutral based on broader market."
      },
      "swing": {
        "score": 0,
        "signal": "NEUTRAL",
        "confidence": 5,
        "reason": "No direct data for agriculture, assuming neutral based on broader market."
      },
      "symbols": [
        "ZC",
        "ZS",
        "ZW",
        "KC",
        "SB",
        "CC",
        "LE",
        "HE"
      ]
    },
    "FX": {
      "intraday": {
        "score": -2,
        "signal": "BEARISH",
        "confidence": 7,
        "reason": "DXY rising, USD strengthening against most major currencies."
      },
      "swing": {
        "score": -2,
        "signal": "BEARISH",
        "confidence": 7,
        "reason": "USD strength likely to continue as risk-off sentiment drives demand for safe haven."
      },
      "symbols": [
        "6E",
        "6A",
        "6J",
        "6B",
        "M6E"
      ]
    },
    "CRYPTO": {
      "intraday": {
        "score": -3,
        "signal": "BEARISH",
        "confidence": 7,
        "reason": "Bitcoin falling, extreme fear index, indicating strong negative sentiment."
      },
      "swing": {
        "score": -3,
        "signal": "BEARISH",
        "confidence": 7,
        "reason": "Extreme fear and falling prices suggest continued downside pressure."
      },
      "symbols": [
        "BTC",
        "ETH",
        "MBT"
      ]
    },
    "VOLATILITY": {
      "intraday": {
        "score": 4,
        "signal": "STRONG_BULLISH",
        "confidence": 8,
        "reason": "VIX rising sharply, backwardation in term structure indicates market stress."
      },
      "swing": {
        "score": 4,
        "signal": "STRONG_BULLISH",
        "confidence": 8,
        "reason": "Rising VIX and backwardation suggest sustained high volatility."
      },
      "symbols": [
        "VX",
        "VXM"
      ]
    }
  },
  "market_data": {
    "vix": {
      "value": 27.44,
      "trend": "rising",
      "change_1d_pct": 8.33
    },
    "dxy": {
      "value": 99.846,
      "trend": "rising",
      "change_5d": 0.266
    },
    "us10y": {
      "value": 4.416,
      "trend": "rising"
    },
    "real_yield_10y": {
      "value": 2.02,
      "trend": "stable"
    },
    "hy_spread": {
      "value": 3.17,
      "trend": "stable"
    },
    "fed_funds_current": 3.64,
    "breakeven_inflation_10y": 2.34,
    "yield_curve_2s10s": 0.46,
    "vix_term_structure": "backwardation",
    "vix_contango_pct": -4.42,
    "gdpnow_estimate_pct": null,
    "eia_crude_change_mb": null,
    "eia_signal": "build",
    "crypto_fear_greed": 13,
    "crypto_fear_greed_label": "Extreme Fear",
    "btc_etf_flow_usd_m": null,
    "gold": 4454.0,
    "crude_oil": 93.9,
    "btc": 68755.8516,
    "sp500": 6477.1602,
    "nasdaq": 23586.9902
  },
  "calendar": {
    "high_impact_today": true,
    "high_impact_events": [
      "Retail Sales m/m"
    ],
    "fomc_days_away": 40,
    "nfp_days_away": 7,
    "in_blackout": false
  },
  "key_drivers": [
    "Equity market sell-off (especially tech)",
    "Rising VIX and backwardation",
    "Rising 10Y Treasury yield"
  ],
  "data_quality": {
    "stale_sources": [
      "NG=F"
    ],
    "fallbacks_used": [
      "NG=F"
    ],
    "validation_corrections": [],
    "notes": "Generated by Matrix Nano Bias Script v1.2 | Run: PRE"
  }
}